Workbook

Sheet Model_Definitions
A1: Synthetic Labor Cost Model: User Guide & Definitions
A3: SHEET 1: INPUTS & ASSUMPTIONS | B3: Definition | C3: Source | D3: Metric Type
A4: Fully Loaded Hourly Rate | B4: Total cost of a human worker per hour (salary + benefits + tax). | C4: HR/Finance | D4: Input
A5: Average Time per Task | B5: Mean duration for a human to complete one workflow cycle. | C5: Operational Logs | D5: Input
A6: Compute/API Cost per Task | B6: Average inference/infrastructure cost (e.g., Vertex AI tokens). | C6: Cloud Billing | D6: Input
A7: Monthly AgentOps Overhead | B7: Fixed cost for orchestration, governance, and technical monitoring. | C7: Eng Budget | D7: Input
A8: Monthly Task Volume | B8: Total throughput required for the 30-day period. | C8: Historical Data | D8: Input
A9: Workflow Candidate | B9: The specific process being evaluated for synthetic labor. | C9: Strategy Team | D9: Input
A11: SHEET 2: ROI MODEL | B11: Definition | C11: Formula / Logic | D11: Metric Type
A12: Human Total Cost | B12: Total spend if work remained 100% human-centric. | C12: Volume * Rate * Time | D12: Output
A13: Synthetic Total Cost | B13: Total spend for AI agents (Compute + Overhead). | C13: (Vol * Comp) + AgentOps | D13: Output
A14: ROI (%) | B14: Efficiency gain relative to the synthetic investment. | C14: (Savings / Synthetic) | D14: KPI
A16: SHEET 3: SENSITIVITY_VOLUME | B16: Definition | C16: Insight Provided | D16: Metric Type
... A31: Strategic Note | B31: Automated recommendation based on Value vs. Risk. | C31: Conditional Logic | D31: Execution Path
A33: HOW TO USE THE MODEL
A34: 1. Baseline | B34: Enter current labor costs and workflow candidate into the "Inputs" sheet.
A35: 2. Pilot | B35: Enter expected API/Infrastructure costs for the agents.
A36: 3. Score | B36: Input telemetry data (violations, escalations) into the Scorecard.
A37: 4. Execute | B37: Follow the "Strategic Note" to Green Light or Redesign.

Sheet Inputs
A1: Category | B1: Parameter | C1: Value | D1: Units | E1: Workflow Candidate | F1: Notes
A2: Human Labor | B2: Fully Loaded Hourly Rate | C2: 50 | D2: USD | E2: Intermodal Customs Exception
A3: Human Labor | B3: Average Time per Task | C3: 1 | D3: Hours
A4: Synthetic Labor | B4: Compute/API Cost per Task | C4: 2 | D4: USD
A5: Synthetic Labor | B5: Monthly AgentOps Overhead | C5: 20000 | D5: USD | F5: Deterministic systems actually lower cost...
A6: Workflow | B6: Monthly Task Volume | C6: 1000 | D6: Tasks | F6: Throughput

Sheet ROI_Model
A1: Metric | B1: Human Baseline | C1: Synthetic Labor | D1: Notes
A2: Total Monthly Volume | B2: =Inputs!C6 -> 1000 | C2: =Inputs!C6 -> 1000
A3: Unit Cost (Labor/Compute) | B3: =Inputs!C2*Inputs!C3 -> 50 | C3: =Inputs!C4 -> 2
A4: Fixed Monthly Overhead | B4: 0 | C4: =Inputs!C5 -> 20000
A5: Total Monthly Cost | B5: =(B2*B3)+B4 -> 50000 | C5: =(C2*C3)+C4 -> 22000
A7: Monthly Savings | B7: =B5-C5 -> 28000
A8: Return on Investment (ROI) | B8: =(B5-C5)/C5 -> 1.2727273

Sheet Sensitivity_Volume
A1: Monthly Volume | B1: Human Cost | C1: Synthetic Cost | D1: ROI %
A2: 500 | B2: =A2 * Inputs!$C$2 * Inputs!$C$3 -> 25000 | C2: =(A2 * Inputs!$C$4) + Inputs!$C$5 -> 21000 | D2: =(B2-C2)/C2 -> 0.19047619
A3: 1000 | B3: =A3 * Inputs!$C$2 * Inputs!$C$3 -> 50000 | C3: =(A3 * Inputs!$C$4) + Inputs!$C$5 -> 22000 | D3: =(B3-C3)/C3 -> 1.2727273
A4: 2500 | B4: =A4 * Inputs!$C$2 * Inputs!$C$3 -> 125000 | C4: =(A4 * Inputs!$C$4) + Inputs!$C$5 -> 25000 | D4: =(B4-C4)/C4 -> 4
A5: 5000 | B5: =A5 * Inputs!$C$2 * Inputs!$C$3 -> 250000 | C5: =(A5 * Inputs!$C$4) + Inputs!$C$5 -> 30000 | D5: =(B5-C5)/C5 -> 7.3333333
A6: 10000 | B6: =A6 * Inputs!$C$2 * Inputs!$C$3 -> 500000 | C6: =(A6 * Inputs!$C$4) + Inputs!$C$5 -> 40000 | D6: =(B6-C6)/C6 -> 11.5

Sheet Sensitivity_Compute
A1: Compute Cost/Task | B1: Human Cost | C1: Synthetic Cost | D1: ROI %
A2: 1 | B2: =Inputs!$C$6 * Inputs!$C$2 * Inputs!$C$3 -> 50000 | C2: =(Inputs!$C$6 * A2) + Inputs!$C$5 -> 21000 | D2: =(B2-C2)/C2 -> 1.3809524
A3: 2 | B3: =Inputs!$C$6 * Inputs!$C$2 * Inputs!$C$3 -> 50000 | C3: =(Inputs!$C$6 * A3) + Inputs!$C$5 -> 22000 | D3: =(B3-C3)/C3 -> 1.2727273
A4: 5 | B4: =Inputs!$C$6 * Inputs!$C$2 * Inputs!$C$3 -> 50000 | C4: =(Inputs!$C$6 * A4) + Inputs!$C$5 -> 25000 | D4: =(B4-C4)/C4 -> 1
A5: 10 | B5: =Inputs!$C$6 * Inputs!$C$2 * Inputs!$C$3 -> 50000 | C5: =(Inputs!$C$6 * A5) + Inputs!$C$5 -> 30000 | D5: =(B5-C5)/C5 -> 0.66666667
A6: 15 | B6: =Inputs!$C$6 * Inputs!$C$2 * Inputs!$C$3 -> 50000 | C6: =(Inputs!$C$6 * A6) + Inputs!$C$5 -> 35000 | D6: =(B6-C6)/C6 -> 0.42857143

Sheet Strategic_Scorecard
A1: Workflow Candidate | B1: ROI (Value) | C1: Policy Violation Rate | D1: Escalation Frequency | E1: Drift Indicator | F1: Strategic Note
A2: =Inputs!E2 -> Intermodal Customs Exception | B2: =ROI_Model!B8 -> 1.2727273 | C2: 0.02 | D2: 0.04 | E2: 0.01 | F2: =IF(AND(B2>1, MAX(C2:E2)<0.05), "Green Light: Ideal for 30-day pilot.", IF(B2>0.5, "High Value/High Risk: Instrument 'Verify' & 'Escalate' before scaling.", "Institutional Drift Trap: Avoid or redesign process.")) -> Green Light: Ideal for 30-day pilot.
A5: Prior Auth (Oncology) | B5: 0.85 | C5: 0.08 | D5: 0.15 | E5: 0.05 | F5: =IF(AND(B5>1, MAX(C5:E5)<0.05), "Green Light: Ideal for 30-day pilot.", IF(B5>0.5, "High Value/High Risk: Instrument 'Verify' & 'Escalate' before scaling.", "Institutional Drift Trap: Avoid or redesign process.")) -> High Value/High Risk: Instrument 'Verify' & 'Escalate' before scaling.
A6: Inverter Anomaly Response | B6: 0.45 | C6: 0.12 | D6: 0.2 | E6: 0.1 | F6: =IF(AND(B6>1, MAX(C6:E6)<0.05), "Green Light: Ideal for 30-day pilot.", IF(B6>0.5, "High Value/High Risk: Instrument 'Verify' & 'Escalate' before scaling.", "Institutional Drift Trap: Avoid or redesign process.")) -> Institutional Drift Trap: Avoid or redesign process.
A7: Routine Triage Agent | B7: 2.1 | C7: 0.01 | D7: 0.02 | E7: 0.005 | F7: =IF(AND(B7>1, MAX(C7:E7)<0.05), "Green Light: Ideal for 30-day pilot.", IF(B7>0.5, "High Value/High Risk: Instrument 'Verify' & 'Escalate' before scaling.", "Institutional Drift Trap: Avoid or redesign process.")) -> Green Light: Ideal for 30-day pilot.
